monqueue.py
MonQueue-0.3.3.dist-info/LICENSE
MonQueue-0.3.3.dist-info/METADATA
MonQueue-0.3.3.dist-info/WHEEL
MonQueue-0.3.3.dist-info/top_level.txt
MonQueue-0.3.3.dist-info/RECORD
