Metadata-Version: 2.1
Name: MonQueue
Version: 0.3.3
Summary: MonQueue is a Python library that allows you to use MongoDB as a message queue.
Home-page: http://rexzhang.github.io/monqueue
Author: Rex Zhang
Author-email: rex.zhang@gmail.com
License: LGPL
Project-URL: Source, https://github.com/rexzhang/monqueue
Keywords: mongodb message-queue
Platform: UNKNOWN
Classifier: Development Status :: 4 - Beta
Classifier: Intended Audience :: Developers
Classifier: License :: OSI Approved :: GNU Lesser General Public License v3 (LGPLv3)
Classifier: Operating System :: OS Independent
Classifier: Programming Language :: Python :: 2
Classifier: Programming Language :: Python :: 2.7
Classifier: Programming Language :: Python :: 3
Classifier: Programming Language :: Python :: 3.5
Classifier: Programming Language :: Python :: 3.6
Classifier: Programming Language :: Python :: 3.7
Classifier: Topic :: Software Development :: Libraries :: Python Modules
Requires-Dist: pymongo
